{"remainingRequest":"/home/vagrant/projects/kibana/build/kibana/node_modules/babel-loader/lib/index.js??ref--6-1!/home/vagrant/projects/kibana/build/kibana/src/ui/public/filter_bar/lib/dedup_filters.js","dependencies":[{"path":"/home/vagrant/projects/kibana/build/kibana/src/ui/public/filter_bar/lib/dedup_filters.js","mtime":1515552035000},{"path":"/home/vagrant/projects/kibana/build/kibana/node_modules/cache-loader/dist/cjs.js","mtime":1493198456000},{"path":"/home/vagrant/projects/kibana/build/kibana/node_modules/babel-loader/lib/index.js","mtime":1503096278000}],"contextDependencies":[],"result":["'use strict';\n\nObject.defineProperty(exports, \"__esModule\", {\n  value: true\n});\nexports.dedupFilters = dedupFilters;\n\nvar _lodash = require('lodash');\n\nvar _lodash2 = _interopRequireDefault(_lodash);\n\nvar _compare_filters = require('ui/filter_bar/lib/compare_filters');\n\nfunction _interopRequireDefault(obj) { return obj && obj.__esModule ? obj : { default: obj }; }\n\n/**\n * Combine 2 filter collections, removing duplicates\n * @param {object} existing The filters to compare to\n * @param {object} filters The filters being added\n * @param {object} comparatorOptions Parameters to use for comparison\n * @returns {object} An array of filters that were not in existing\n */\nfunction dedupFilters(existingFilters, filters, comparatorOptions) {\n  if (!Array.isArray(filters)) filters = [filters];\n\n  return _lodash2.default.filter(filters, function (filter) {\n    return !_lodash2.default.find(existingFilters, function (existingFilter) {\n      return (0, _compare_filters.compareFilters)(existingFilter, filter, comparatorOptions);\n    });\n  });\n}",null]}