{"remainingRequest":"/home/vagrant/projects/kibana/build/kibana/node_modules/babel-loader/lib/index.js??ref--6-1!/home/vagrant/projects/kibana/build/kibana/src/core_plugins/metrics/public/components/lib/convert_series_to_vars.js","dependencies":[{"path":"/home/vagrant/projects/kibana/build/kibana/src/core_plugins/metrics/public/components/lib/convert_series_to_vars.js","mtime":1515552029000},{"path":"/home/vagrant/projects/kibana/build/kibana/node_modules/cache-loader/dist/cjs.js","mtime":1493198456000},{"path":"/home/vagrant/projects/kibana/build/kibana/node_modules/babel-loader/lib/index.js","mtime":1503096278000}],"contextDependencies":[],"result":["'use strict';\n\nObject.defineProperty(exports, \"__esModule\", {\n  value: true\n});\n\nvar _lodash = require('lodash');\n\nvar _lodash2 = _interopRequireDefault(_lodash);\n\nvar _get_last_value = require('../../visualizations/lib/get_last_value');\n\nvar _get_last_value2 = _interopRequireDefault(_get_last_value);\n\nvar _tick_formatter = require('./tick_formatter');\n\nvar _tick_formatter2 = _interopRequireDefault(_tick_formatter);\n\nvar _moment = require('moment');\n\nvar _moment2 = _interopRequireDefault(_moment);\n\nfunction _interopRequireDefault(obj) { return obj && obj.__esModule ? obj : { default: obj }; }\n\nexports.default = function (series, model) {\n  var dateFormat = arguments.length > 2 && arguments[2] !== undefined ? arguments[2] : 'lll';\n\n  var variables = {};\n  model.series.forEach(function (seriesModel) {\n    series.filter(function (row) {\n      return _lodash2.default.startsWith(row.id, seriesModel.id);\n    }).forEach(function (row) {\n      var varName = [_lodash2.default.snakeCase(row.label), _lodash2.default.snakeCase(seriesModel.var_name)].filter(function (v) {\n        return v;\n      }).join('.');\n\n      var formatter = (0, _tick_formatter2.default)(seriesModel.formatter, seriesModel.value_template);\n      var lastValue = (0, _get_last_value2.default)(row.data, 10);\n\n      var data = {\n        last: {\n          raw: lastValue,\n          formatted: formatter(lastValue)\n        },\n        data: {\n          raw: row.data,\n          formatted: row.data.map(function (point) {\n            return [(0, _moment2.default)(point[0]).format(dateFormat), formatter(point[1])];\n          })\n        }\n      };\n      _lodash2.default.set(variables, varName, data);\n      _lodash2.default.set(variables, _lodash2.default.snakeCase(row.label) + '.label', row.label);\n    });\n  });\n  return variables;\n};\n\nmodule.exports = exports['default'];",null]}