{"remainingRequest":"/home/vagrant/projects/kibana/build/kibana/node_modules/babel-loader/lib/index.js??ref--6-1!/home/vagrant/projects/kibana/build/kibana/src/ui/public/vislib/vislib.js","dependencies":[{"path":"/home/vagrant/projects/kibana/build/kibana/src/ui/public/vislib/vislib.js","mtime":1515552039000},{"path":"/home/vagrant/projects/kibana/build/kibana/node_modules/cache-loader/dist/cjs.js","mtime":1493198456000},{"path":"/home/vagrant/projects/kibana/build/kibana/node_modules/babel-loader/lib/index.js","mtime":1503096278000}],"contextDependencies":[],"result":["'use strict';\n\nObject.defineProperty(exports, \"__esModule\", {\n  value: true\n});\nexports.VislibProvider = VislibProvider;\n\nrequire('./lib/types/pie');\n\nrequire('./lib/types/point_series');\n\nrequire('./lib/types');\n\nrequire('./lib/layout/layout_types');\n\nrequire('./lib/data');\n\nrequire('./visualizations/vis_types');\n\nrequire('./styles/main.less');\n\nvar _vis = require('./vis');\n\n// prefetched for faster optimization runs\n// end prefetching\n\n/**\n * Provides the Kibana4 Visualization Library\n *\n * @module vislib\n * @main vislib\n * @return {Object} Contains the version number and the Vis Class for creating visualizations\n */\nfunction VislibProvider(Private) {\n  return {\n    version: '0.0.0',\n    Vis: Private(_vis.VislibVisProvider)\n  };\n}",null]}